tpy/__init__.py
tpy/__main__.py
tpy/config.py
tpy/jsonc.py
tpy/tpy.py
TPython-1.8.3.dist-info/LICENSE
TPython-1.8.3.dist-info/METADATA
TPython-1.8.3.dist-info/WHEEL
TPython-1.8.3.dist-info/entry_points.txt
TPython-1.8.3.dist-info/top_level.txt
TPython-1.8.3.dist-info/RECORD
